README.md
setup.cfg
setup.py
src/atopile/__init__.py
src/atopile/build.py
src/atopile/cli.py
src/atopile/config_manager.py
src/atopile/init_project.py
src/atopile/lib.py
src/atopile/options.py
src/atopile/resources.py
src/atopile/scan.py
src/atopile/stages.py
src/atopile/tree.py
src/atopile/utils.py
src/atopile_cli.egg-info/PKG-INFO
src/atopile_cli.egg-info/SOURCES.txt
src/atopile_cli.egg-info/dependency_links.txt
src/atopile_cli.egg-info/entry_points.txt
src/atopile_cli.egg-info/requires.txt
src/atopile_cli.egg-info/top_level.txt