Metadata-Version: 2.1
Name: atopile-cli
Version: 0.1.10
Summary: The atopile command line interface.
Home-page: https://atopile.io/
Author: Matthew Wildoer
Author-email: mawildoer@gmail.com
Requires-Python: >=3.8
